aiwatchdog_sdk/__init__.py
aiwatchdogco-0.0.1.dist-info/METADATA
aiwatchdogco-0.0.1.dist-info/WHEEL
aiwatchdogco-0.0.1.dist-info/top_level.txt
aiwatchdogco-0.0.1.dist-info/RECORD
