Metadata-Version: 2.4
Name: aiwatchdogco
Version: 0.0.1
Summary: Placeholder package to reserve the aiwatchdog name.
Author-email: Jeet Parekh <jp@aiwatchdog.co>
License-Expression: MIT
Requires-Python: >=3.7
